pyshipproto/__init__.py
pyshipproto/auth/__init__.py
pyshipproto/auth/auth_pb2.py
pyshipproto/auth/auth_pb2_grpc.py
pyshipproto/crud/__init__.py
pyshipproto/crud/crud_pb2.py
pyshipproto/crud/crud_pb2_grpc.py
pyshipproto/executor/__init__.py
pyshipproto/executor/executor_pb2.py
pyshipproto/executor/executor_pb2_grpc.py
pyshipproto-2.7.0.dist-info/METADATA
pyshipproto-2.7.0.dist-info/WHEEL
pyshipproto-2.7.0.dist-info/top_level.txt
pyshipproto-2.7.0.dist-info/RECORD
