Metadata-Version: 2.1
Name: pyshipproto
Version: 2.7.0
Summary: PyShipProto Package
Home-page: https://github.com/shipthisco/gRPC-protobuf
Author: PyShipProto
Author-email: <pyshipproto@gmail.com>
Keywords: python,gRPC,protobuf,pyshipproto
Classifier: Development Status :: 3 - Alpha
Classifier: Intended Audience :: Developers
Classifier: Programming Language :: Python :: 3
Classifier: Programming Language :: Python :: 3.8
Classifier: Programming Language :: Python :: 3.9
Classifier: Programming Language :: Python :: 3.10
Classifier: Programming Language :: Python :: 3.11
Classifier: Programming Language :: Python :: 3.12
Classifier: Operating System :: OS Independent
Requires-Python: >=3.8
Requires-Dist: grpcio>=1.48.0
Requires-Dist: grpcio-tools>=1.48.0
Requires-Dist: protobuf<7.0.0,>=4.21.0
